{"success": true, "data": {"artistGid": "5987c5f2cae44ed68856ca0bd43a5dc6", "name": "ACH0", "mainImageUrl": "https://i.scdn.co/image/ab67616100005174f31d43b5348f63d3a851c4f3", "headerImage": {"id": "ab676186fc2af45f34137f75ca314d25", "uri": "https://i.scdn.co/image/ab6761860000101603d50ba0cbec808a35ceb2da", "width": 2660, "height": 1140}, "autobiography": {"body": "Bulgarian trapper,rapper from the capital of Bulgaria , SOFIA. Ach0 was born on 10th of May 1999 in Sofia neighbourhood MLADOST. He studied in music school and played the piano  , he started rapping at early age. His first record was when he was 21 but he didn&#39;t upload it it was just for fun . Ach0 is the creator of MGL gang (MladostGangLifestyle) and his first official song is with his big bro Pameca from Murda Boyz when he was 23.\n ", "links": {"facebook": "https://facebook.com/Ach0MGL/", "instagram": "https://instagram.com/achodimitrov/"}}, "images": [{"id": "ab67616708d2e00017156db8b220e655", "uri": "https://i.scdn.co/image/ab6761670000ecd4f72d1fffe8ea92474ddf19aa", "width": 640, "height": 640}], "imagesCount": 1, "globalChartPosition": 0, "monthlyListeners": 858, "monthlyListenersDelta": 240, "followerCount": 84, "followingCount": 0, "playlists": {"entries": [{"uri": "spotify:user:31uahdqor577yesx3txmjdjdyaui:playlist:0VnbEkYWQVFgsF8TXl3k66", "name": "Murda Boyz Collection ", "imageUrl": "https://i.scdn.co/image/ab67706c0000da84326c3b1769f5dd651bcedb89", "owner": {"name": "MUZE Music", "uri": "spotify:user:31uahdqor577yesx3txmjdjdyaui"}, "listeners": 0}, {"uri": "spotify:user:rkxq31j1tck67jtninrd04h5s:playlist:0PJacF9Mf1GN91zgsg6yEq", "name": "\u041f\u0410\u041c\u0415\u0426\u0410\u0410\ud83d\udc79", "imageUrl": "https://mosaic.scdn.co/300/ab67616d00001e0241ee1960727f440eac0a6eebab67616d00001e025b453fdb71d14d86831e2b0cab67616d00001e02664e1f5e03f9ab546a0a32a7ab67616d00001e028d6d3aac0a1593f3ebdf8cc9", "owner": {"name": ".", "uri": "spotify:user:rkxq31j1tck67jtninrd04h5s"}, "listeners": 0}, {"uri": "spotify:user:03iepya7sqinbjojfov13e86v:playlist:1mjzQedLUC64bAC1b1lqdm", "name": "samo elitni pesni", "imageUrl": "https://i.scdn.co/image/ab67706c0000da84dad96c5e14d0553c89f36e86", "owner": {"name": "Kaloarsov", "uri": "spotify:user:03iepya7sqinbjojfov13e86v"}, "listeners": 0}, {"uri": "spotify:user:31yu76obdnna2gf4xjj4eb3segyu:playlist:0Rs9RI8S4Cbj5cq7oriHt8", "name": "1", "imageUrl": "https://mosaic.scdn.co/300/ab67616d00001e0261ade4c888fc6502462e47d4ab67616d00001e02bd588dd05712558936ba9a86ab67616d00001e02e419f6d8cf5ace702fb55883ab67616d00001e02f86f93bad2120c7ad37f34bc", "owner": {"name": "Kalinsoftov", "uri": "spotify:user:31yu76obdnna2gf4xjj4eb3segyu"}, "listeners": 0}, {"uri": "spotify:user:31yvzeypx6irj6pdk3hgia3nhgse:playlist:3HKiWxnSIX90aHXyeFocIO", "name": "Maznotiqq", "imageUrl": "https://i.scdn.co/image/ab67706c0000da84c19d9731d0662faa99debbc7", "owner": {"name": "jorginho", "uri": "spotify:user:31yvzeypx6irj6pdk3hgia3nhgse"}, "listeners": 0}, {"uri": "spotify:user:in1en224zfj9of8vci7e684hg:playlist:7yhWO2BQe1Jla8Nkap721M", "name": "Fyre & MBT & Upsurt & 100Kila & Secta", "imageUrl": "https://i.scdn.co/image/ab67706c0000da84c371e4898f0d207cce57848a", "owner": {"name": "tonkataEK9", "uri": "spotify:user:in1en224zfj9of8vci7e684hg"}, "listeners": 0}]}, "cities": [{"country": "BG", "region": "22", "city": "Sofia", "listeners": 541}, {"country": "BG", "region": "03", "city": "Varna", "listeners": 67}, {"country": "BG", "region": "02", "city": "Burgas", "listeners": 45}, {"country": "BG", "region": "16", "city": "Plovdiv", "listeners": 29}, {"country": "RS", "region": "00", "city": "Belgrade", "listeners": 10}, {"country": "BG", "region": "15", "city": "Pleven", "listeners": 10}, {"country": "BG", "region": "18", "city": "Rousse", "listeners": 10}, {"country": "BG", "region": "24", "city": "Stara Zagora", "listeners": 8}, {"country": "GB", "region": "ENG", "city": "London", "listeners": 6}, {"country": "BG", "region": "14", "city": "Pernik", "listeners": 6}, {"country": "BG", "region": "20", "city": "Sliven", "listeners": 6}, {"country": "BG", "region": "01", "city": "Blagoevgrad", "listeners": 5}, {"country": "DE", "region": "HE", "city": "Frankfurt am Main", "listeners": 4}, {"country": "GR", "region": "B", "city": "Thessaloniki", "listeners": 4}, {"country": "GR", "region": "I", "city": "Athens", "listeners": 4}, {"country": "AT", "region": "9", "city": "Vienna", "listeners": 4}, {"country": "BG", "region": "07", "city": "Gabrovo", "listeners": 4}, {"country": "BG", "region": "17", "city": "Razgrad", "listeners": 4}, {"country": "BG", "region": "11", "city": "Lovech", "listeners": 4}, {"country": "BG", "region": "08", "city": "Dobrich", "listeners": 4}, {"country": "HR", "region": "21", "city": "Zagreb", "listeners": 3}, {"country": "BA", "region": "SRP", "city": "Banja Luka", "listeners": 3}, {"country": "BG", "region": "06", "city": "Vratsa", "listeners": 3}, {"country": "BG", "region": "10", "city": "Kyustendil", "listeners": 3}, {"country": "BG", "region": "24", "city": "Kazanlak", "listeners": 3}, {"country": "BG", "region": "13", "city": "Pazardzhik", "listeners": 3}, {"country": "BG", "region": "16", "city": "Rakovski", "listeners": 3}, {"country": "BG", "region": "19", "city": "Silistra", "listeners": 3}, {"country": "BG", "region": "22", "city": "Novi Iskar", "listeners": 3}, {"country": "BE", "region": "BRU", "city": "Brussels", "listeners": 2}, {"country": "DE", "region": "NW", "city": "Dortmund", "listeners": 2}, {"country": "DE", "region": "BE", "city": "Berlin", "listeners": 2}, {"country": "DE", "region": "BY", "city": "Augsburg", "listeners": 2}, {"country": "ME", "region": "16", "city": "Podgorica", "listeners": 2}, {"country": "GB", "region": "ENG", "city": "Newham", "listeners": 2}, {"country": "GB", "region": "ENG", "city": "Kilburn", "listeners": 2}, {"country": "GB", "region": "ENG", "city": "Fulham", "listeners": 2}, {"country": "GB", "region": "ENG", "city": "Hounslow", "listeners": 2}, {"country": "NL", "region": "NH", "city": "Amsterdam", "listeners": 2}, {"country": "BG", "region": "01", "city": "Bansko", "listeners": 2}, {"country": "BG", "region": "13", "city": "Peshtera", "listeners": 2}, {"country": "BG", "region": "12", "city": "Montana", "listeners": 2}, {"country": "BG", "region": "28", "city": "Yambol", "listeners": 2}, {"country": "BG", "region": "14", "city": "Radomir", "listeners": 2}, {"country": "BG", "region": "03", "city": "Provadia", "listeners": 2}, {"country": "BG", "region": "16", "city": "Karlovo", "listeners": 2}, {"country": "BG", "region": "27", "city": "Shumen", "listeners": 2}, {"country": "BG", "region": "04", "city": "Gorna Oryahovitsa", "listeners": 2}, {"country": "BG", "region": "05", "city": "Vidin", "listeners": 2}, {"country": "BE", "region": "BRU", "city": "Uccle", "listeners": 1}]}}