{"success": true, "data": {"artistGid": "fef9f860520148b98003d82ab7a49550", "name": "Buch", "mainImageUrl": "https://i.scdn.co/image/ab676161000051742149b12f70f65e17bdc3a2f9", "headerImage": {"id": "ab6761867175ff3ba547ba98370f584f", "uri": "https://i.scdn.co/image/ab676186000010168e8a00c45ab84567c8f0a7b0", "width": 2660, "height": 1140}, "autobiography": {"links": {"facebook": "https://facebook.com/BUCH.Music", "instagram": "https://instagram.com/buch.entertainment"}}, "images": [{"id": "a98dac510c3245448508ad131371fa4c", "uri": "https://i.scdn.co/image/0a5168991c387ad7010939e49ffddb66074201c4", "width": 640, "height": 640}, {"id": "d22e9ff1e11041b79a35c3ef530c816e", "uri": "https://i.scdn.co/image/964ab1f6178551400ef5f5d985f43b005f3c3787", "width": 640, "height": 640}, {"id": "3f1ef4a4e3884925a23d1c41e6d2c896", "uri": "https://i.scdn.co/image/a51d2e8e05daa48aac08081b6c6fb35daca6e332", "width": 640, "height": 640}], "imagesCount": 3, "globalChartPosition": 0, "monthlyListeners": 333, "monthlyListenersDelta": 5, "followerCount": 284, "followingCount": 0, "playlists": {"entries": [{"uri": "spotify:user:31w4ymnotk2o3geerfgcbrt3gluy:playlist:5k9pEp4sLmiFM7wzwu9eWl", "name": "GOLD BG HIP-HOP", "imageUrl": "https://mosaic.scdn.co/300/ab67616d00001e0204bc09bf5dd21db2bff9bcccab67616d00001e02095a513fb0f6dc328b4fa502ab67616d00001e0224c9711ea48b2d967c41b898ab67616d00001e02fcb920e112bd999d14221df4", "owner": {"name": "ivanoffbg", "uri": "spotify:user:31w4ymnotk2o3geerfgcbrt3gluy"}, "listeners": 0}, {"uri": "spotify:user:31sa3gifncxnj2gqsltaxquv2okq:playlist:3BTemD2VkOpyPPMkB6CaPb", "name": "Rap Mix", "imageUrl": "https://i.scdn.co/image/ab67706c0000da84c64c6b742ac94411e6bab34d", "owner": {"name": "bahoszy", "uri": "spotify:user:31sa3gifncxnj2gqsltaxquv2okq"}, "listeners": 0}]}, "cities": [{"country": "BG", "region": "22", "city": "Sofia", "listeners": 223}, {"country": "BG", "region": "03", "city": "Varna", "listeners": 28}, {"country": "BG", "region": "16", "city": "Plovdiv", "listeners": 16}, {"country": "BG", "region": "02", "city": "Burgas", "listeners": 6}, {"country": "NL", "region": "ZH", "city": "Rotterdam", "listeners": 4}, {"country": "GB", "region": "ENG", "city": "London", "listeners": 4}, {"country": "NL", "region": "NH", "city": "Amsterdam", "listeners": 3}, {"country": "BG", "region": "15", "city": "Pleven", "listeners": 3}, {"country": "BG", "region": "01", "city": "Blagoevgrad", "listeners": 3}, {"country": "DE", "region": "HE", "city": "Frankfurt am Main", "listeners": 3}, {"country": "BG", "region": "18", "city": "Rousse", "listeners": 2}, {"country": "BG", "region": "27", "city": "Shumen", "listeners": 2}, {"country": "BG", "region": "23", "city": "Samokov", "listeners": 2}, {"country": "UA", "region": "77", "city": "Chernivtsi", "listeners": 2}, {"country": "AT", "region": "9", "city": "Vienna", "listeners": 2}, {"country": "BE", "region": "BRU", "city": "Brussels", "listeners": 2}, {"country": "CZ", "region": "10", "city": "Prague", "listeners": 2}, {"country": "NL", "region": "ZH", "city": "Zoetermeer", "listeners": 1}, {"country": "NL", "region": "ZH", "city": "Leiden", "listeners": 1}, {"country": "NL", "region": "ZH", "city": "Schiedam", "listeners": 1}, {"country": "NL", "region": "LI", "city": "Maastricht", "listeners": 1}, {"country": "NL", "region": "ZH", "city": "The Hague", "listeners": 1}, {"country": "NL", "region": "ZH", "city": "Waddinxveen", "listeners": 1}, {"country": "SE", "region": "X", "city": "G\u00e4vle", "listeners": 1}, {"country": "NO", "region": "03", "city": "Oslo", "listeners": 1}, {"country": "BG", "region": "13", "city": "Bratsigovo", "listeners": 1}, {"country": "BG", "region": "24", "city": "Kazanlak", "listeners": 1}, {"country": "BG", "region": "24", "city": "Stara Zagora", "listeners": 1}, {"country": "BG", "region": "16", "city": "Hisarya", "listeners": 1}, {"country": "BG", "region": "22", "city": "Malashevtsi", "listeners": 1}, {"country": "BG", "region": "13", "city": "Govedare", "listeners": 1}, {"country": "BG", "region": "08", "city": "Dobrich", "listeners": 1}, {"country": "BG", "region": "23", "city": "Svoge", "listeners": 1}, {"country": "BG", "region": "06", "city": "Vratsa", "listeners": 1}, {"country": "BG", "region": "07", "city": "Gabrovo", "listeners": 1}, {"country": "BG", "region": "28", "city": "Yambol", "listeners": 1}, {"country": "BG", "region": "23", "city": "Kostinbrod", "listeners": 1}, {"country": "BG", "region": "10", "city": "Kyustendil", "listeners": 1}, {"country": "UA", "region": "30", "city": "Kyiv", "listeners": 1}, {"country": "UA", "region": "26", "city": "Ivano-Frankivsk", "listeners": 1}, {"country": "UA", "region": "12", "city": "Dnipro", "listeners": 1}, {"country": "DE", "region": "BW", "city": "Stuttgart", "listeners": 1}, {"country": "DE", "region": "BE", "city": "Berlin", "listeners": 1}, {"country": "DE", "region": "HH", "city": "Hamburg", "listeners": 1}, {"country": "DE", "region": "NW", "city": "Bonn", "listeners": 1}, {"country": "DE", "region": "SH", "city": "Escheburg", "listeners": 1}, {"country": "DE", "region": "NW", "city": "Cologne", "listeners": 1}, {"country": "DE", "region": "BW", "city": "Besigheim", "listeners": 1}, {"country": "DE", "region": "ST", "city": "Magdeburg", "listeners": 1}, {"country": "CA", "region": "ON", "city": "Toronto", "listeners": 1}]}}