{"success": true, "data": {"artistGid": "6d8dcc0469eb48c0a81f1ba7d8632ee3", "name": "Homelesz", "mainImageUrl": "https://i.scdn.co/image/ab67616d00001e02136a6d83bfa27e5e39be3231", "globalChartPosition": 0, "monthlyListeners": 8601, "monthlyListenersDelta": -762, "followerCount": 7485, "followingCount": 0, "playlists": {"entries": [{"uri": "spotify:user:11186775505:playlist:44lxcVy25MbtGPVYhZqeTj", "name": "BG RAP \u0417\u0410 \u0414\u0423\u0428\u0410\u0422\u0410", "imageUrl": "https://i.scdn.co/image/ab67706c0000da84c0b55838aa3305577975bc75", "owner": {"name": "\u0414\u0438\u043c\u0438\u0442\u044a\u0440 \u041a\u0440\u044a\u0441\u0442\u0430\u043d\u043e\u0432", "uri": "spotify:user:11186775505"}, "listeners": 0}, {"uri": "spotify:user:uzmrstc3uy8fwx0xdmpasq4yi:playlist:4mDf5dxnYQJIcZtH9ZmtPH", "name": "\u041c\u0411\u0422", "imageUrl": "https://mosaic.scdn.co/300/ab67616d00001e023fcab8a7d5b36cdde6a8bbb3ab67616d00001e026ed2e6ce04d5a6c11b9486a0ab67616d00001e0281aeb07c2d0e0018e8c95c8dab67616d00001e02b422f8d5dc0f18da8283a985", "owner": {"name": "shamanaXD", "uri": "spotify:user:uzmrstc3uy8fwx0xdmpasq4yi"}, "listeners": 0}, {"uri": "spotify:user:31m4462dbjfpkvn3acolfi6xrkte:playlist:5bT3UGQXy3kvwdD28HChBL", "name": "MBT/MurdaBoyz", "imageUrl": "https://i.scdn.co/image/ab67706c0000da84fc2926fbd1c3b2f284439d44", "owner": {"name": "\u041c\u0430\u0440\u0442\u043e \u0414\u0436.", "uri": "spotify:user:31m4462dbjfpkvn3acolfi6xrkte"}, "listeners": 0}, {"uri": "spotify:user:31twax2xn2o7z2hg5lr6pgv7qvrq:playlist:6xUZO1AXd0SOg8hgDVvCfc", "name": "Fyre workout", "imageUrl": "https://mosaic.scdn.co/300/ab67616d00001e0215e7b5b065748e3970e48a8cab67616d00001e02cfb6b2390bc7f4a8ab3274a5ab67616d00001e02dfe3239a575ccec93ac28e02ab67616d00001e02ef03478bae942855270785b7", "owner": {"name": "KOCATAKANGAL", "uri": "spotify:user:31twax2xn2o7z2hg5lr6pgv7qvrq"}, "listeners": 0}, {"uri": "spotify:user:chavozila:playlist:47GiiPM5JORbbTNP761x3V", "name": "BG Trap/Rap Mix", "imageUrl": "https://mosaic.scdn.co/300/ab67616d00001e0240e3b2c5cbfd84e4f81b1eefab67616d00001e026bf2d4cda56bf919b34519f8ab67616d00001e02aede18b21a19c8232f819fcbab67616d00001e02ef03478bae942855270785b7", "owner": {"name": "Chavo", "uri": "spotify:user:chavozila"}, "listeners": 0}, {"uri": "spotify:user:213xtxuixy3gxtxtjniiavqdy:playlist:48VUizWjQ5ubVseLFQvYLU", "name": "MBT BNR DVA SREDNI PRUSTA ZA MVR", "imageUrl": "https://mosaic.scdn.co/300/ab67616d00001e0222e673924ff3bbc0d9e5e6deab67616d00001e02b9c0e2c2db80fd1f5f3b9aceab67616d00001e02c201d251cd229ebd832a1917ab67616d00001e02eacbcb328abc7c8540e5037f", "owner": {"name": "Alex Malinov", "uri": "spotify:user:213xtxuixy3gxtxtjniiavqdy"}, "listeners": 0}, {"uri": "spotify:user:ure1gqcphsl5gcmda9awnsqut:playlist:3oZ5EZvqh4sKjX5NRdEpHj", "name": "KARTELA RECORDS", "imageUrl": "https://i.scdn.co/image/ab67706c0000da84c0ceba636bc1fcc9b0439aff", "owner": {"name": "G4M3R", "uri": "spotify:user:ure1gqcphsl5gcmda9awnsqut"}, "listeners": 0}, {"uri": "spotify:user:mvgmmcdwk707a8q3owmnitnyz:playlist:1wg4HIgjmfIuAspijZxWuw", "name": "E.C.C.C. ( EAST COAST CASH CREW )", "imageUrl": "https://i.scdn.co/image/ab67706c0000da8479226e43584e7b5c87794ebc", "owner": {"name": "EXC", "uri": "spotify:user:mvgmmcdwk707a8q3owmnitnyz"}, "listeners": 0}, {"uri": "spotify:user:raikov02:playlist:4fvKd3E6z97WOMs12CZCy0", "name": "BG RAP", "imageUrl": "https://i.scdn.co/image/ab67706c0000da849079753506e3ab3543df1bf5", "owner": {"name": "\u0420\u043e\u0441\u0442\u0438\u0441\u043b\u0430\u0432 \u0420\u0430\u0439\u043a\u043e\u0432", "uri": "spotify:user:raikov02"}, "listeners": 0}, {"uri": "spotify:user:uvb0ivqj3au2kfs9oi8wvhdjv:playlist:7KmvKUh9JG95pKHON4pQ0H", "name": "Car Mix BG \ud83d\udd0a\ud83c\udde7\ud83c\uddec", "imageUrl": "https://i.scdn.co/image/ab67706c0000da84da0aa24b954cbb7d6a43e721", "owner": {"name": "Kaloyan", "uri": "spotify:user:uvb0ivqj3au2kfs9oi8wvhdjv"}, "listeners": 0}]}, "cities": [{"country": "BG", "region": "22", "city": "Sofia", "listeners": 5170}, {"country": "BG", "region": "03", "city": "Varna", "listeners": 744}, {"country": "BG", "region": "02", "city": "Burgas", "listeners": 310}, {"country": "BG", "region": "16", "city": "Plovdiv", "listeners": 291}, {"country": "GB", "region": "ENG", "city": "London", "listeners": 101}, {"country": "BG", "region": "24", "city": "Stara Zagora", "listeners": 93}, {"country": "BG", "region": "18", "city": "Rousse", "listeners": 93}, {"country": "BG", "region": "15", "city": "Pleven", "listeners": 51}, {"country": "NL", "region": "NH", "city": "Amsterdam", "listeners": 50}, {"country": "DE", "region": "BE", "city": "Berlin", "listeners": 50}, {"country": "BG", "region": "20", "city": "Sliven", "listeners": 42}, {"country": "BG", "region": "14", "city": "Pernik", "listeners": 41}, {"country": "NL", "region": "ZH", "city": "Rotterdam", "listeners": 40}, {"country": "BG", "region": "01", "city": "Blagoevgrad", "listeners": 40}, {"country": "DE", "region": "HE", "city": "Frankfurt am Main", "listeners": 39}, {"country": "BG", "region": "27", "city": "Shumen", "listeners": 35}, {"country": "BG", "region": "06", "city": "Vratsa", "listeners": 35}, {"country": "BG", "region": "26", "city": "Haskovo", "listeners": 35}, {"country": "BG", "region": "09", "city": "Kardzhali", "listeners": 34}, {"country": "AT", "region": "9", "city": "Vienna", "listeners": 33}, {"country": "BG", "region": "10", "city": "Kyustendil", "listeners": 30}, {"country": "BG", "region": "08", "city": "Dobrich", "listeners": 30}, {"country": "DE", "region": "BY", "city": "Munich", "listeners": 29}, {"country": "BG", "region": "07", "city": "Gabrovo", "listeners": 29}, {"country": "BG", "region": "05", "city": "Vidin", "listeners": 28}, {"country": "CZ", "region": "10", "city": "Prague", "listeners": 28}, {"country": "BG", "region": "17", "city": "Razgrad", "listeners": 27}, {"country": "BG", "region": "13", "city": "Pazardzhik", "listeners": 27}, {"country": "BG", "region": "24", "city": "Kazanlak", "listeners": 25}, {"country": "DE", "region": "HH", "city": "Hamburg", "listeners": 24}, {"country": "BG", "region": "04", "city": "Gorna Oryahovitsa", "listeners": 24}, {"country": "GB", "region": "ENG", "city": "Southwark", "listeners": 22}, {"country": "DE", "region": "BW", "city": "Stuttgart", "listeners": 21}, {"country": "BE", "region": "BRU", "city": "Brussels", "listeners": 21}, {"country": "BG", "region": "12", "city": "Montana", "listeners": 20}, {"country": "BG", "region": "28", "city": "Yambol", "listeners": 20}, {"country": "FR", "region": "IDF", "city": "Paris", "listeners": 19}, {"country": "DE", "region": "NW", "city": "Cologne", "listeners": 17}, {"country": "BG", "region": "21", "city": "Smolyan", "listeners": 17}, {"country": "GB", "region": "ENG", "city": "Birmingham", "listeners": 17}, {"country": "ES", "region": "MD", "city": "Madrid", "listeners": 17}, {"country": "TR", "region": "34", "city": "Istanbul", "listeners": 16}, {"country": "GR", "region": "I", "city": "Athens", "listeners": 15}, {"country": "BG", "region": "23", "city": "Samokov", "listeners": 14}, {"country": "BG", "region": "01", "city": "Petrich", "listeners": 14}, {"country": "BG", "region": "01", "city": "Sandanski", "listeners": 14}, {"country": "NL", "region": "NB", "city": "Eindhoven", "listeners": 13}, {"country": "BG", "region": "26", "city": "Svilengrad", "listeners": 13}, {"country": "BG", "region": "26", "city": "Dimitrovgrad", "listeners": 13}, {"country": "BG", "region": "16", "city": "Asenovgrad", "listeners": 13}]}}