{"success": true, "data": {"artistGid": "36573636a152487a9bef7e1565ddeb2d", "name": "MZM13", "mainImageUrl": "https://i.scdn.co/image/ab67616100005174a2ec43b20456459657bbf64e", "headerImage": {"id": "ab6761862b3c0819035e840f1e07538e", "uri": "https://i.scdn.co/image/ab67618600001016d4c3f7e6fca17bf0e1f8ac71", "width": 2660, "height": 1140}, "autobiography": {}, "globalChartPosition": 0, "monthlyListeners": 638, "monthlyListenersDelta": -84, "followerCount": 512, "followingCount": 0, "playlists": {"entries": [{"uri": "spotify:user:spotify:playlist:37i9dQZF1DZ06evO3gC3XZ", "name": "This Is Shunaka", "imageUrl": "https://thisis-images.spotifycdn.com/37i9dQZF1DZ06evO3gC3XZ-default.jpg", "owner": {"name": "Spotify", "uri": "spotify:user:spotify"}, "listeners": 0}, {"uri": "spotify:user:3cdgazhcy0ytun770ear8e46p:playlist:2aA2er5k4F0XFxkfxzwC9t", "name": "RapHub", "imageUrl": "https://i.scdn.co/image/ab67706c0000da84467cdc03b10ff34a16011ac8", "owner": {"name": "Malkiq", "uri": "spotify:user:3cdgazhcy0ytun770ear8e46p"}, "listeners": 0}, {"uri": "spotify:user:31lonbeewvyru7hwrzeuizls2vfm:playlist:0eDEzIN8yDguBCCiUd2qUB", "name": "\ud83d\udde3\ufe0f", "imageUrl": "https://i.scdn.co/image/ab67706c0000da84650f1c3363566f53b60bfd45", "owner": {"name": "Aleki", "uri": "spotify:user:31lonbeewvyru7hwrzeuizls2vfm"}, "listeners": 0}, {"uri": "spotify:user:jackdaniel540:playlist:2FfWhvM7JOWA7JBcYtgYRH", "name": "Ego", "imageUrl": "https://i.scdn.co/image/ab67706c0000da847f2ea2c1c5a58905f39dedb8", "owner": {"name": "offfdanieeel", "uri": "spotify:user:jackdaniel540"}, "listeners": 0}, {"uri": "spotify:user:313pd4pbtwi3fgq4dk4sk5vyb75m:playlist:6VUX6GY3dJ5EprIUbi8jDU", "name": "777", "imageUrl": "https://mosaic.scdn.co/300/ab67616d00001e0246fa945f4255657a7b6e7fcfab67616d00001e026c18c8d5d29e4191e09fff88ab67616d00001e02a3bc87a929bc3b643bfc90dcab67616d00001e02dbd52a51f0ad634f2de95f38", "owner": {"name": "Mitashki_Tashki", "uri": "spotify:user:313pd4pbtwi3fgq4dk4sk5vyb75m"}, "listeners": 0}, {"uri": "spotify:user:bozhidar251:playlist:5GUEoeuw49ugG8fFzHl5Ax", "name": "brat", "imageUrl": "https://i.scdn.co/image/ab67706c0000da844c174264c7c864e1a7f59829", "owner": {"name": "bozhidar251", "uri": "spotify:user:bozhidar251"}, "listeners": 0}, {"uri": "spotify:user:312s3prxgzhttvzvzhrxdrdvvrr4:playlist:6Kn6gl3cwopPRCAUofz6EC", "name": "Ludi gi praim", "imageUrl": "https://i.scdn.co/image/ab67706c0000da8453f33ce0aaee57357d555d2b", "owner": {"name": "Vesela Mihailova", "uri": "spotify:user:312s3prxgzhttvzvzhrxdrdvvrr4"}, "listeners": 0}, {"uri": "spotify:user:31bhdx2xr7ztx7al3cdnqp3cu2mq:playlist:1ULAvroPxNTu1SEcQuwCmB", "name": "Hui", "imageUrl": "https://mosaic.scdn.co/300/ab67616d00001e021eb7c13c1b4d84080cd44e15ab67616d00001e023da6737c50b7fb62d9c6ba6cab67616d00001e0289dca842f2ff2a8fea731f1fab67616d00001e02fb0fb9ec6f8aaebb836bb042", "owner": {"name": "Nn158_W", "uri": "spotify:user:31bhdx2xr7ztx7al3cdnqp3cu2mq"}, "listeners": 0}, {"uri": "spotify:user:11175851791:playlist:1wcYN31RotPuiIWSFKcHm5", "name": "Murda x MBT x T19C \ud83c\udff4\u200d\u2620\ufe0f", "imageUrl": "https://i.scdn.co/image/ab67706c0000da84400d5a490735e18b8ad4439d", "owner": {"name": "Kriskata", "uri": "spotify:user:11175851791"}, "listeners": 0}, {"uri": "spotify:user:gc4lufc941gho4j2vz9qrc51f:playlist:2S7qojfkTKtQsmVr7yFblL", "name": "tarikata i shunaka sa neshto moshtno", "imageUrl": "https://i.scdn.co/image/ab67706c0000da8401c6c2d3e3c7f85b6c6519a4", "owner": {"name": "808wave", "uri": "spotify:user:gc4lufc941gho4j2vz9qrc51f"}, "listeners": 0}]}, "cities": [{"country": "BG", "region": "22", "city": "Sofia", "listeners": 340}, {"country": "BG", "region": "03", "city": "Varna", "listeners": 104}, {"country": "BG", "region": "02", "city": "Burgas", "listeners": 37}, {"country": "BG", "region": "16", "city": "Plovdiv", "listeners": 22}, {"country": "BG", "region": "15", "city": "Pleven", "listeners": 7}, {"country": "BG", "region": "24", "city": "Stara Zagora", "listeners": 5}, {"country": "RO", "region": "B", "city": "Bucharest", "listeners": 4}, {"country": "GB", "region": "ENG", "city": "London", "listeners": 4}, {"country": "CZ", "region": "10", "city": "Prague", "listeners": 4}, {"country": "BG", "region": "04", "city": "Gorna Oryahovitsa", "listeners": 4}, {"country": "BG", "region": "18", "city": "Rousse", "listeners": 4}, {"country": "NL", "region": "ZH", "city": "Rotterdam", "listeners": 4}, {"country": "BE", "region": "BRU", "city": "Brussels", "listeners": 4}, {"country": "GB", "region": "ENG", "city": "Southwark", "listeners": 3}, {"country": "AT", "region": "9", "city": "Vienna", "listeners": 3}, {"country": "TR", "region": "34", "city": "Istanbul", "listeners": 3}, {"country": "GR", "region": "I", "city": "Athens", "listeners": 3}, {"country": "CO", "region": "VAC", "city": "Santiago de Cali", "listeners": 3}, {"country": "BG", "region": "03", "city": "Devnya", "listeners": 3}, {"country": "BG", "region": "12", "city": "Montana", "listeners": 3}, {"country": "BG", "region": "25", "city": "Popovo", "listeners": 3}, {"country": "NL", "region": "NH", "city": "Amsterdam", "listeners": 3}, {"country": "UA", "region": "30", "city": "Kyiv", "listeners": 3}, {"country": "MK", "region": "211", "city": "Shtip", "listeners": 2}, {"country": "RO", "region": "BV", "city": "Brasov", "listeners": 2}, {"country": "GB", "region": "SCT", "city": "Glasgow", "listeners": 2}, {"country": "ME", "region": "16", "city": "Podgorica", "listeners": 2}, {"country": "MD", "region": "CU", "city": "Chisinau", "listeners": 2}, {"country": "AM", "region": "ER", "city": "Yerevan", "listeners": 2}, {"country": "BG", "region": "02", "city": "Aytos", "listeners": 2}, {"country": "BG", "region": "26", "city": "Svilengrad", "listeners": 2}, {"country": "BG", "region": "20", "city": "Sliven", "listeners": 2}, {"country": "BG", "region": "10", "city": "Kyustendil", "listeners": 2}, {"country": "BG", "region": "25", "city": "Targovishte", "listeners": 2}, {"country": "BG", "region": "19", "city": "Silistra", "listeners": 2}, {"country": "BG", "region": "01", "city": "Blagoevgrad", "listeners": 2}, {"country": "BG", "region": "04", "city": "Sistov", "listeners": 2}, {"country": "BG", "region": "08", "city": "Baltchik", "listeners": 2}, {"country": "BG", "region": "09", "city": "Kardzhali", "listeners": 2}, {"country": "CA", "region": "AB", "city": "Calgary", "listeners": 2}, {"country": "DE", "region": "BY", "city": "Munich", "listeners": 2}, {"country": "HR", "region": "21", "city": "Zagreb", "listeners": 2}, {"country": "SK", "region": "KI", "city": "Ko\u0161ice", "listeners": 2}, {"country": "RS", "region": "00", "city": "Belgrade", "listeners": 2}, {"country": "LT", "region": "VL", "city": "Vilnius", "listeners": 2}, {"country": "KZ", "region": "55", "city": "Pavlodar", "listeners": 2}, {"country": "BY", "region": "HM", "city": "Minsk", "listeners": 2}, {"country": "RO", "region": "VL", "city": "R\u00e2mnicu V\u00e2lcea", "listeners": 1}, {"country": "RO", "region": "TR", "city": "Alexandria", "listeners": 1}, {"country": "RO", "region": "PH", "city": "Ploie\u015fti", "listeners": 1}]}}