{"success": true, "data": {"artistGid": "3c1f0fdf28bd45518df059a30d4631ab", "name": "Novem", "mainImageUrl": "https://i.scdn.co/image/ab67616100005174dcea3099b8df72809b9f0929", "headerImage": {"id": "ab676186b48b4bfa4229eb8ec25af504", "uri": "https://i.scdn.co/image/ab676186000010164b74b405bdd614713da50afb", "width": 2660, "height": 1140}, "autobiography": {"body": "1/6 \u041e\u0422 \u041f\u042a\u041b\u041d\u0410 \u0421\u041a\u0420\u042a\u0411 \u041c\u042a\u0420\u0422\u042a\u0412 \u041a\u041b\u0410\u041d.\n\u2028\nebem ti i undergrounda. \n ", "links": {"facebook": "https://facebook.com/novem.wav.9/", "instagram": "https://instagram.com/novem.umre/?hl=en"}}, "images": [{"id": "ab676167ec6157afca56d9238db35de8", "uri": "https://i.scdn.co/image/ab6761670000ecd4139ea85035a926dc724ca217", "width": 640, "height": 640}, {"id": "ab6761670bc91bf4cc15b6941c0b5c3d", "uri": "https://i.scdn.co/image/ab6761670000ecd4f436e40b33ea496be3f4a3c2", "width": 640, "height": 640}, {"id": "ab67616799d74bec02e68866831f9da1", "uri": "https://i.scdn.co/image/ab6761670000ecd46628b413fd1977997ce0625e", "width": 640, "height": 640}, {"id": "ab6761674e54eebf5b9680aa89fc3355", "uri": "https://i.scdn.co/image/ab6761670000ecd4b1ab1140a4697f557603ccaa", "width": 640, "height": 640}], "imagesCount": 4, "globalChartPosition": 0, "monthlyListeners": 274, "monthlyListenersDelta": -14, "followerCount": 502, "followingCount": 0, "playlists": {"entries": [{"uri": "spotify:user:asen.popov:playlist:4LFnQZxjjeONhP9KpPf7FI", "name": "\u0416\u043b\u044a\u0447/\u0413\u0440\u0438\u0433\u043e\u0432\u043e\u0440/\u0413\u0435\u043d\u0430", "imageUrl": "https://mosaic.scdn.co/300/ab67616d00001e02275777781994ab7e76adad99ab67616d00001e028ef6c40618368c7060fff5bcab67616d00001e02a239c7daf7396c0358fe31f2ab67616d00001e02c8803368ced102f397ef9a37", "owner": {"name": "asen.popov", "uri": "spotify:user:asen.popov"}, "listeners": 0}, {"uri": "spotify:user:gerry_cherry_b:playlist:1Fcc5pHSJLnxpmUjP5KwEO", "name": "\u041f\u0421\u041c\u041a\ud83d\udc80\ud83d\udd2a", "imageUrl": "https://i.scdn.co/image/ab67706c0000da847edca8e64e6f7d2f12ec938c", "owner": {"name": "Gergana Slavcheva", "uri": "spotify:user:gerry_cherry_b"}, "listeners": 0}, {"uri": "spotify:user:darozavur:playlist:6oeS3wHfvFbPZ9xL4sadGL", "name": "Tor23", "imageUrl": "https://mosaic.scdn.co/300/ab67616d00001e0206facb3b9474f0d6fb098cf2ab67616d00001e02554331f739a38de59342b38bab67616d00001e028a3584c73c623038dc34cdc6ab67616d00001e02c1b211b5fcdef31be5f806df", "owner": {"name": "Darina Banova", "uri": "spotify:user:darozavur"}, "listeners": 0}, {"uri": "spotify:user:daftkqfnbyvti2wr4tr20dtcx:playlist:2X5D6hqJHnTPP0t36rtm9a", "name": "Secty-sect", "imageUrl": "https://mosaic.scdn.co/300/ab67616d00001e0220bead17c71189b6e05da96aab67616d00001e0237c5725f78f53d9485e6f8edab67616d00001e02d4129bea868e9b289d586493ab67616d00001e02f7dc4a2a538d93827d0294e0", "owner": {"name": "dasyuri", "uri": "spotify:user:daftkqfnbyvti2wr4tr20dtcx"}, "listeners": 0}]}, "cities": [{"country": "BG", "region": "22", "city": "Sofia", "listeners": 196}, {"country": "BG", "region": "03", "city": "Varna", "listeners": 24}, {"country": "BG", "region": "02", "city": "Burgas", "listeners": 9}, {"country": "BG", "region": "16", "city": "Plovdiv", "listeners": 7}, {"country": "BG", "region": "21", "city": "Smolyan", "listeners": 5}, {"country": "BG", "region": "08", "city": "Dobrich", "listeners": 4}, {"country": "BG", "region": "05", "city": "Vidin", "listeners": 4}, {"country": "DE", "region": "BE", "city": "Berlin", "listeners": 3}, {"country": "BG", "region": "24", "city": "Stara Zagora", "listeners": 3}, {"country": "BG", "region": "06", "city": "Vratsa", "listeners": 3}, {"country": "NL", "region": "NH", "city": "Amsterdam", "listeners": 3}, {"country": "GB", "region": "ENG", "city": "London", "listeners": 3}, {"country": "FR", "region": "IDF", "city": "Paris", "listeners": 2}, {"country": "IT", "region": "25", "city": "Milan", "listeners": 2}, {"country": "BG", "region": "23", "city": "Samokov", "listeners": 2}, {"country": "BG", "region": "26", "city": "Haskovo", "listeners": 2}, {"country": "NL", "region": "ZH", "city": "Rotterdam", "listeners": 2}, {"country": "GB", "region": "ENG", "city": "Southwark", "listeners": 2}, {"country": "GB", "region": "ENG", "city": "Hayes", "listeners": 2}, {"country": "RS", "region": "00", "city": "Belgrade", "listeners": 1}, {"country": "CZ", "region": "10", "city": "Prague", "listeners": 1}, {"country": "CO", "region": "DC", "city": "Bogot\u00e1", "listeners": 1}, {"country": "TR", "region": "51", "city": "Ni\u011fde", "listeners": 1}, {"country": "DE", "region": "HE", "city": "Frankfurt am Main", "listeners": 1}, {"country": "DK", "region": "84", "city": "Copenhagen", "listeners": 1}, {"country": "IT", "region": "62", "city": "Rome", "listeners": 1}, {"country": "IT", "region": "45", "city": "Rimini", "listeners": 1}, {"country": "IT", "region": "25", "city": "Bollate", "listeners": 1}, {"country": "IT", "region": "21", "city": "Turin", "listeners": 1}, {"country": "AU", "region": "QLD", "city": "Brisbane", "listeners": 1}, {"country": "BG", "region": "20", "city": "Sliven", "listeners": 1}, {"country": "BG", "region": "16", "city": "Perushtitsa", "listeners": 1}, {"country": "BG", "region": "10", "city": "Dupnitsa", "listeners": 1}, {"country": "BG", "region": "21", "city": "Dospat", "listeners": 1}, {"country": "BG", "region": "24", "city": "Kazanlak", "listeners": 1}, {"country": "BG", "region": "23", "city": "Elin Pelin", "listeners": 1}, {"country": "BG", "region": "11", "city": "Lovech", "listeners": 1}, {"country": "BG", "region": "23", "city": "Kostenets", "listeners": 1}, {"country": "BG", "region": "04", "city": "Gorna Oryahovitsa", "listeners": 1}, {"country": "BG", "region": "13", "city": "Pazardzhik", "listeners": 1}, {"country": "BG", "region": "16", "city": "Sopot", "listeners": 1}, {"country": "BG", "region": "18", "city": "Borovo", "listeners": 1}, {"country": "BG", "region": "07", "city": "Dryanovo", "listeners": 1}, {"country": "BG", "region": "16", "city": "Rakovski", "listeners": 1}, {"country": "BG", "region": "26", "city": "Dimitrovgrad", "listeners": 1}, {"country": "BG", "region": "01", "city": "Blagoevgrad", "listeners": 1}, {"country": "BG", "region": "18", "city": "Rousse", "listeners": 1}, {"country": "BG", "region": "24", "city": "Chirpan", "listeners": 1}, {"country": "BG", "region": "16", "city": "Kostievo", "listeners": 1}, {"country": "BG", "region": "22", "city": "Nadezhda", "listeners": 1}]}}