{"success": true, "data": {"artistGid": "877e6a90131e45ada4850e9d5328f656", "name": "TEDO", "mainImageUrl": "https://i.scdn.co/image/ab67616100005174e8db773803ed11144be756e8", "autobiography": {}, "globalChartPosition": 0, "monthlyListeners": 25, "monthlyListenersDelta": 23, "followerCount": 13, "followingCount": 0, "cities": [{"country": "BG", "region": "22", "city": "Sofia", "listeners": 9}, {"country": "BG", "region": "03", "city": "Varna", "listeners": 8}, {"country": "RO", "region": "B", "city": "Bucharest", "listeners": 1}, {"country": "IT", "region": "25", "city": "Rogeno", "listeners": 1}, {"country": "LT", "region": "KU", "city": "Kaunas", "listeners": 1}, {"country": "KZ", "region": "23", "city": "Atyrau", "listeners": 1}, {"country": "UZ", "region": "TK", "city": "Tashkent", "listeners": 1}, {"country": "BG", "region": "08", "city": "Dobrich", "listeners": 1}, {"country": "BG", "region": "18", "city": "Rousse", "listeners": 1}, {"country": "BG", "region": "02", "city": "Burgas", "listeners": 1}, {"country": "AM", "region": "ER", "city": "Yerevan", "listeners": 1}, {"country": "RS", "region": "00", "city": "Belgrade", "listeners": 1}, {"country": "RS", "region": "19", "city": "Kru\u0161evac", "listeners": 1}]}}